{"anno":[{"width":4000,"height":2667,"tw":1200,"th":800,"alt":"","index":0,"blurhash":"L4CiBh5D01-302tRVqNH00Mc}sxw"},{"width":4000,"height":2667,"tw":1200,"th":800,"alt":"","index":1,"blurhash":"L9H1JSzD0#Q5?HpHD%VZ0LtQMdn5"},{"width":3000,"height":4000,"tw":1200,"th":1600,"alt":"","index":2,"blurhash":"LRKTiBIU_M=|~VMyM|t7Ips.D%S#"},{"width":4000,"height":2667,"tw":1200,"th":800,"alt":"","index":3,"blurhash":"LRG+UJNY00%M_Nt1E0S#xtWAR*WX"},{"width":4000,"height":2666,"tw":1200,"th":800,"alt":"","index":4,"blurhash":"LFEx#71c9F~C.SnPSMNFK4r@kDI."},{"width":4000,"height":3000,"tw":1200,"th":900,"alt":"","index":5,"blurhash":"LN7d^,NNIlxaKBoMxBS7o0ohWVR*"},{"width":2667,"height":4000,"tw":1200,"th":1800,"alt":"","index":6,"blurhash":"L5Hn231v00*w_0000nA300#7~q.T"},{"width":4000,"height":2667,"tw":1200,"th":800,"alt":"","index":7,"blurhash":"LQF6m?MyAA.R?[RkRQtQI;W.m:ax"},{"width":4000,"height":2667,"tw":1200,"th":800,"alt":"","index":8,"blurhash":"LYHw_lS%D*s:_Nf9RjkCx^RjR*j["},{"width":2667,"height":4000,"tw":1200,"th":1800,"alt":"","index":9,"blurhash":"LJGQ@D~9tm$~?IW,o#WA0g4:Rnoc"},{"width":4000,"height":3200,"tw":1200,"th":960,"alt":"","index":10,"blurhash":"L4C=rJMd00^5sp}@^PRO00ae_4Io"},{"width":4000,"height":2590,"tw":1200,"th":777,"alt":"","index":11,"blurhash":"LCD]0YxZ00aK0rEN}-%1jXxZW?Ne"},{"width":4000,"height":2667,"tw":1200,"th":800,"alt":"","index":12,"blurhash":"LJDb+*_1ofn,~Wt7R*t759D*NGxv"},{"width":2667,"height":4000,"tw":1200,"th":1800,"alt":"","index":13,"blurhash":"LLAAky4mtpWH-iIwjptUIQx^RUxs"},{"width":4000,"height":2667,"tw":1200,"th":800,"alt":"","index":14,"blurhash":"LZ6[w%R,Rgs+x|WYW9ocMukCofWY"},{"width":4000,"height":2667,"tw":1200,"th":800,"alt":"","index":15,"blurhash":"L9D0is+X*^]fGwW+I9nj00O[E2M}"},{"width":4000,"height":2667,"tw":1200,"th":800,"alt":"","index":16,"blurhash":"L9D9nt~nE2Olt%X4jZkS01RU%KnT"},{"width":3508,"height":4000,"tw":1200,"th":1368,"alt":"","index":17,"blurhash":"LAG7e-:8ZPxbuf-BEMOB0fY3X7J6"},{"width":4000,"height":2250,"tw":1200,"th":675,"alt":"","index":18,"blurhash":"LLD9AXELM]%3%QNes=s;9rxwogRh"},{"width":4000,"height":2667,"tw":1200,"th":800,"alt":"","index":19,"blurhash":"LVGIo@_NI;yDozxts+V?RkWVRjRj"},{"width":4000,"height":2667,"tw":1200,"th":800,"alt":"","index":20,"blurhash":"LpHx4=?b%No~~B%gtStRsmX8W;n$"},{"width":3017,"height":3017,"tw":1200,"th":1200,"alt":"","index":21,"blurhash":"LCDT8|%|0xM_PxMyRRpG00Mx}v%f"},{"width":4000,"height":2667,"tw":1200,"th":800,"alt":"","index":22,"blurhash":"LKF}yY?ck?tT_4-Voyxuo~nONGRk"},{"width":3000,"height":4000,"tw":1200,"th":1600,"alt":"","index":23,"blurhash":"LIGQ|U-:0LRj00IV~V-oF{xaM_M|"}],"bluttribut":[{"width":1200,"height":916,"tw":1200,"th":916,"alt":"Johann (Leon Rörig) treibt im Dorf sein Unwesen","index":0,"blurhash":"L69i--;K1i2m8weT5lEyuhKO;z||"},{"width":1200,"height":800,"tw":1200,"th":800,"alt":"Das ganze Ensemble","index":1,"blurhash":"L59$^1M_0f-99^E3E2Ef01~B=_S5"},{"width":1200,"height":859,"tw":1200,"th":859,"alt":"Bürgermeister Albert (Sebastian Sattler) und Wirt Otto (Leonhard Rikart) planen das Dorffest","index":2,"blurhash":"L48;fQ0J00~CBr-2DOI^4m^k*058"},{"width":1200,"height":927,"tw":1200,"th":927,"alt":"Ehestreit im Hause des Bürgermeisters","index":3,"blurhash":"L4BL;U1h01}o8{9[s9E20i%L~B%M"},{"width":1200,"height":863,"tw":1200,"th":863,"alt":"Hans (Till Michel) hat aus Versehen Emma, die Tochter des Bürgermeisters, (Toni Kummermehr) in einer unangenehmen Situation kennengelernt","index":4,"blurhash":"LLEVTZ%00MM}~UxXE3Iq0MNH%Kof"},{"width":1200,"height":754,"tw":1200,"th":754,"alt":"Ida (Anna Kummermehr) hat Emma, ihrer großen Schwester(Toni Kummermehr) ,einen Streich gespielt. Ihre Mutter (Marleen Pohl) greift ein.","index":5,"blurhash":"LA9%6nOTtP~CM_WAt7sl5QxHNK9Z"},{"width":1200,"height":802,"tw":1200,"th":802,"alt":"Emma (Toni Kummermehr) trifft Lisa (Carina Sattler), ihre beste Freundin","index":6,"blurhash":"L7ASxzV?0fK7{vIn1INerUXnTLrq"},{"width":1200,"height":802,"tw":1200,"th":802,"alt":"Hans (Till Michel) macht Emma (Toni Kummermehr) den Hof","index":7,"blurhash":"L1717i0p00Dh0X~A$u5600-4?cx_"},{"width":1200,"height":555,"tw":1200,"th":555,"alt":"Das Dorffest ist in vollem Gange","index":8,"blurhash":"LA9s@]9tQ+rt~7I;n3V[EKtSn,I:"},{"width":1200,"height":681,"tw":1200,"th":681,"alt":"Emma (Toni Kummermehr) wurde als Bluttribut erwählt","index":9,"blurhash":"LA8X00}3I8FkRqX7aIs,0_A0tSx8"},{"width":1200,"height":668,"tw":1200,"th":668,"alt":"Der Graf (Anton Rikart) begrüßt den Tribut auf seinem Anwesen","index":10,"blurhash":"LHBh~N00T[##$GRgndRq00?=nBNe"},{"width":1200,"height":796,"tw":1200,"th":796,"alt":"Hausgeist Anastasia (Anna Rieder) hilft Emmas Freunden","index":11,"blurhash":"LGC~bZ~A0g02-7nhShSi4:NHxZ?F"},{"width":1200,"height":831,"tw":1200,"th":831,"alt":"Der Graf (Anton Rikart) macht Emma (Toni Kummermehr) ein Geschenk","index":12,"blurhash":"L37^Y,20MJ9t$kXn}@560K^KtlNK"},{"width":1200,"height":649,"tw":1200,"th":649,"alt":"Emma (Toni Kummermehr) hat einen Alptraum, in dem ihre gute Seite (Marleen Pohl) und ihre dunkle Seite (Carina Sattler) miteinander kämpfen","index":13,"blurhash":"L~E0Vf$qf3WTS1fUjsfNWVWUa~fP"},{"width":1200,"height":801,"tw":1200,"th":801,"alt":"Die Nacht der Nächte ist gekommen","index":14,"blurhash":"L5Nh=l?[?FIt5Z0UO-1c342Urri_"},{"width":1200,"height":784,"tw":1200,"th":784,"alt":"Der Graf (Anton Rikart) bittet Emma (Toni Kummermehr) zu einem letzten Tanz","index":15,"blurhash":"LDF;aZ00n2~E0c=dxbwQIIb[g3E1"},{"width":1200,"height":868,"tw":1200,"th":868,"alt":"Hans (Till Michel) versucht mit Ida (Anna Kummermehr) und Lisa (Carina Sattler), Emma (Toni Kummermehr) zu retten","index":16,"blurhash":"L7Ci8fV?DhO[00tR~CIAEcoc-B-U"},{"width":1200,"height":1074,"tw":1200,"th":1074,"alt":"Bürgermeister Albert (Sebastian Sattler) kann seine verloren geglaubte Tochter wieder in die Arme schließen","index":17,"blurhash":"LXDbHF589t~BInxaS$RiOss9enT0"},{"width":1200,"height":1013,"tw":1200,"th":1013,"alt":"Applaus beim großen Finale","index":18,"blurhash":"LQBfi6r-oixwImD#bJWA-@Rgt9jX"},{"width":1200,"height":1812,"tw":1200,"th":1812,"alt":"Der Graf naht","index":19,"blurhash":"L99OGj|{so|w2s70Fc6Nso,s]Uwd"},{"width":1200,"height":795,"tw":1200,"th":795,"alt":"Der letzte Tanz","index":20,"blurhash":"L94_k+nmM_xu9WX5xvRjtWjuWBkB"}],"dystopia":[{"width":1200,"height":907,"tw":1200,"th":907,"alt":"Vyper (Francesco Santamaria) erhält von Lily (Anna Rieder) interessante Neuigkeiten","index":0,"blurhash":"LDHBe%?^01EN.8%h9gS501IW-oxu"},{"width":1200,"height":755,"tw":1200,"th":755,"alt":"Cobra (Carina Sattler)","index":1,"blurhash":"LCEePo~S.O~A04018}IuAC?YT0bv"},{"width":1200,"height":801,"tw":1200,"th":801,"alt":"Danksagungen von Regisseur Sebastian Sattler nach der Premiere","index":2,"blurhash":"LEFE.T?H0f00NfE3t7-U00E2-o~V"},{"width":1200,"height":795,"tw":1200,"th":795,"alt":"Die Free werden von den Snakes gefangen gehalten","index":3,"blurhash":"LBD[Ia~A0KE27KI;rEj?5Rof?Gsl"},{"width":1200,"height":1812,"tw":1200,"th":1812,"alt":"Cat (Luisa Stark)","index":4,"blurhash":"L77xT,y+Ip#:03VLwJK1qyZ*ozr["},{"width":1200,"height":1812,"tw":1200,"th":1812,"alt":"Summer (Nora Bidinger), Lilly (Anna Rieder) und Moon (Jasmin Stricker)","index":5,"blurhash":"LECZeU?Fxs_4-q?dn-M_i^%gtRIT"},{"width":1200,"height":800,"tw":1200,"th":800,"alt":"Die Free proben den Aufstand gegen die Herrschaft der Snakes","index":6,"blurhash":"L4A9jJ$k0e+t00EhtSMx00$*}tX;"},{"width":1200,"height":800,"tw":1200,"th":800,"alt":"Mira (Marleen Pohl) erzählt Cobra (Carina Sattler) ihre Geschichte","index":7,"blurhash":"L8Akwm|{A9X4}7#?sqob0]J5$lWZ"},{"width":1200,"height":1083,"tw":1200,"th":1083,"alt":"Mira (Marleen Pohl) kümmert sich um Cat (Luisa Stark)","index":8,"blurhash":"LBFhq~E100^k02o#VXIU2]=v}?AI"},{"width":1200,"height":716,"tw":1200,"th":716,"alt":"Mira (Marleen Pohl) und Moon (Jasmin Stricker)","index":9,"blurhash":"L7HK^R?]jJ0000T1^0A^?]4-vy.S"},{"width":1200,"height":735,"tw":1200,"th":735,"alt":"Die Snakes rüsten sich zum Schlag gegen die Free","index":10,"blurhash":"L16RGxi{Ni4TQ800.S=;.S:zo*R:"},{"width":1200,"height":794,"tw":1200,"th":794,"alt":"Mira (Marleen Pohl)","index":11,"blurhash":"L37KYoNz0000$2v|JWOs00Mx?c~q"},{"width":1200,"height":784,"tw":1200,"th":784,"alt":"Moon (Anna Kummermehr) und Mira (Marleen Pohl) beratschlagen sich","index":12,"blurhash":"L8BfIZ=YDO~A#SjG%0$f02xbtRE1"},{"width":1200,"height":801,"tw":1200,"th":801,"alt":"&quot;Fasst sie!&quot;","index":13,"blurhash":"LSHwuv~nxuX.ESE2ROoHE3M|IUaJ"},{"width":1200,"height":682,"tw":1200,"th":682,"alt":"&quot;Ich bin entstellt!&quot;","index":14,"blurhash":"L6EL~T0C00%f00^$_4sD00?5}AR4"},{"width":1200,"height":797,"tw":1200,"th":797,"alt":"Alan (Anton Rikart) verzweifelt nach dem Tod von Richy","index":15,"blurhash":"LE9t7~4}s$Ii_0N7N5RjNWxuD?%1"},{"width":1200,"height":725,"tw":1200,"th":725,"alt":"Die Free schöpfen neue Hoffnung!","index":16,"blurhash":"L38DkM0i009}~WS09FIv02-Q-;xZ"},{"width":1200,"height":801,"tw":1200,"th":801,"alt":"Moon (Anna Kummermehr) möchte Cat (Luisa Stark) vor einer Dummheit bewahren","index":17,"blurhash":"LKB3EC~A$y%F$+s;R:RnE2SdtQS5"},{"width":1200,"height":996,"tw":1200,"th":996,"alt":"Vyper (Francesco Santamaria) verhört Moon (Anna Kummermehr)","index":18,"blurhash":"L6FpsiTx0$D4x^}t}Y0z00r=XR?a"}],"freiheit":[{"width":1200,"height":800,"tw":1200,"th":800,"alt":"Carmen (Magdalena Misling) erzählt gerne Abenteuergeschichten","index":0,"blurhash":"L7By,IH?00%14n-W%3In00-q~W9a"},{"width":1200,"height":1800,"tw":1200,"th":1800,"alt":"Sophia (Luisa stark) hält nichts von klassischen Rollenbildern","index":1,"blurhash":"L9D+e_~C0KAJ1ko~nNxu01Eg^j,B"},{"width":1200,"height":800,"tw":1200,"th":800,"alt":"Admiral Rodrigo (Fynn Hüttmann) verhört die gefangene Anne Bonny (Lea Bohn)","index":2,"blurhash":"L4EeS#4:02-P00^k~Bof00-U^jxI"},{"width":1200,"height":800,"tw":1200,"th":800,"alt":"Sophia (Luisa Stark) möchte alles über das abenteuerliche Leben als Piratin erfahren","index":3,"blurhash":"LAI|aV},03E2~BxY-o-T02NL?F?F"},{"width":1200,"height":1600,"tw":1200,"th":1600,"alt":"Matteo (Franek Wozniak) und Laurent (Anton Rikart) suchen sich einen neuen Job","index":4,"blurhash":"LJG[7{F60J0e1nxcnxs703w[%1=_"},{"width":1200,"height":800,"tw":1200,"th":800,"alt":"Isabella (Maria Misling) ist genervt von Laurents (Anton Rikart) Menüideen","index":5,"blurhash":"LBBfhQ-;0z4T~VxtI:IV0JIU%2%h"},{"width":1200,"height":960,"tw":1200,"th":960,"alt":"Blackbeard (Louis Noe) heuert eine neue Crew an","index":6,"blurhash":"L9GGkkKb0Ktn~Cg3wIxb58bI%LM{"},{"width":1200,"height":800,"tw":1200,"th":800,"alt":"Anne Bonny (Lea Bohn) gelingt die Flucht aus den Verliesen der Spanier","index":7,"blurhash":"LMCsN.%ME2~W9EE1R*V?M_WVbbRP"},{"width":1200,"height":800,"tw":1200,"th":800,"alt":"Sophia (Luisa stark) wird (mehr oder weniger unfreiwillig) zur Piratin","index":8,"blurhash":"L7B:ml0K00?Z00^*%$RP4:Ne~Wn$"},{"width":1200,"height":800,"tw":1200,"th":800,"alt":"Capitan Javier (Sebastian Sattler) jagt die Piraten","index":9,"blurhash":"L8C64D0LX-kYpy-9eq.7MwkqS%$f"},{"width":1200,"height":1800,"tw":1200,"th":1800,"alt":"Blackbeard (Louis Noe) sticht in See","index":10,"blurhash":"L5Ci8gcF3X~V01DiHq9G7L~V-WFz"},{"width":1200,"height":1800,"tw":1200,"th":1800,"alt":"Mary Read (Carina Sattler) kommt hinter Sophias Geheimnis","index":11,"blurhash":"L5Acb,4n02^+-pi_9u%200%3~V9Z"},{"width":1200,"height":900,"tw":1200,"th":900,"alt":"Anne (Lea Bohn) erzählt von ihrer Vergangenheit","index":12,"blurhash":"LbC6KS%PWms$OetAt1t0IUR:xVob"},{"width":1200,"height":800,"tw":1200,"th":800,"alt":"Megan (Nele Rörig) und Jolene (Nora Bidinger) planen mit Laurent gemeinsam Sophias Rettung","index":13,"blurhash":"L4E_Q[8x000KB$Tc}Fzq00~B_2%#"},{"width":1200,"height":681,"tw":1200,"th":681,"alt":"Mary (Carina Sattler) befreit Anne mit einem großen KABOOMM!","index":14,"blurhash":"L9CYXNDj5T~V,p%1JTxW00t+-m9G"},{"width":1200,"height":800,"tw":1200,"th":800,"alt":"Rodrigo (Fynn Hüttmann) steht kurz vor seinem Ziel...","index":15,"blurhash":"L39QBw0200^$Z}-oT39b00~U~WN4"},{"width":1200,"height":800,"tw":1200,"th":800,"alt":"...wird dann aber noch rechtzeitig aufgehalten.","index":16,"blurhash":"L79?w$9p4m0p0uV:$[?J0j-9$_%3"},{"width":1200,"height":800,"tw":1200,"th":800,"alt":"Anne Bonny (Lea Bohn) und Jack Rackham (Yunus Sari)","index":17,"blurhash":"LCEUx?~W0fDi01IA%2-;5Rs.jZs;"},{"width":1200,"height":675,"tw":1200,"th":675,"alt":"Das gesamte Ensemble bei der Verbeugung","index":18,"blurhash":"L18DnX9]0y~V~VE2R%%200wH=|57"},{"width":1200,"height":1600,"tw":1200,"th":1600,"alt":"Carmen (Magdalena Misling) versucht die Wachen zu überzeugen","index":19,"blurhash":"LDDb7$~Bo#%M9bRiRjof9G58EMM{"},{"width":1200,"height":800,"tw":1200,"th":800,"alt":"Die Piraten suchen ein neues Schiff","index":20,"blurhash":"LNELd6DO_M9ZFy9Zt8RPEfniaLxa"},{"width":1200,"height":800,"tw":1200,"th":800,"alt":"Die Feierstimmung der Piraten...","index":21,"blurhash":"L4C5hpBp0#0}03%1kWIq00#l-U}?"},{"width":1200,"height":800,"tw":1200,"th":800,"alt":"... wird durch einen unerwarteten Besuch unterbrochen!","index":22,"blurhash":"L7GiTF=z1cK#2@KN-At601|F-AEN"}],"goldfieber":[{"width":1200,"height":800,"tw":1200,"th":800,"alt":"Ben (Leon Rörig) und Frank (Louis Noe) bekommen die Nachricht von ihrer Erbschaft","index":0,"blurhash":"L9ATp4Dhov-oK8McM{Rj.SMw?wM{"},{"width":1200,"height":800,"tw":1200,"th":800,"alt":"Im Westen geht es wild her","index":1,"blurhash":"L7A]~eE+Dgac00oeWBWq.lxBx_xv"},{"width":1200,"height":800,"tw":1200,"th":800,"alt":"&quot;In der verlassenen Mine soll es wohl einen Schatz geben.&quot;","index":2,"blurhash":"L7AA8trWD%%O00%MtSM^~WRPe-t8"},{"width":1200,"height":800,"tw":1200,"th":800,"alt":"Im Saloon ist viel los…","index":3,"blurhash":"L5ATTPEN01^+00x[?IM{uiV?r=OY"},{"width":1200,"height":1800,"tw":1200,"th":1800,"alt":"... und es wird dem Glücksspiel gefröhnt.","index":4,"blurhash":"L4C6li00~W_ND$_3f+xu00^4Ef8_"},{"width":1200,"height":800,"tw":1200,"th":800,"alt":"Kate macht sich schick um den Erben der Mine zu verführen.","index":5,"blurhash":"L59i#h0i#P0M0M^N5S}@01nh^*$*"},{"width":1200,"height":800,"tw":1200,"th":800,"alt":"Bei Doc (Sebastian Sattler) stößt Kate mit ihren Avancen allerdings auf taube Ohren.","index":6,"blurhash":"L7Bp2[~C?IM}BPNxELoL00V@,:$%"},{"width":1200,"height":800,"tw":1200,"th":800,"alt":"Auch bei Ben scheint es nicht klappen zu wollen.","index":7,"blurhash":"LPCZ9J~WE14oRkays:of004.xu?H"},{"width":1200,"height":1800,"tw":1200,"th":1800,"alt":"Maggy (Carina Sattler)","index":8,"blurhash":"L59HCJ=_~T%30JD%4oxbI*%gtSIU"},{"width":1200,"height":1800,"tw":1200,"th":1800,"alt":"Kaum zurück in der alten Heimat, wird sie erkannt.","index":9,"blurhash":"L9CGGZ?w~VOu9EV@IUs+00Mdo{Vr"},{"width":1200,"height":800,"tw":1200,"th":800,"alt":"Auch Morgan Bullock (Anton Rikart) ist mit seiner Bande hinter der Mine her…","index":10,"blurhash":"LHF}j0xw_N2tGF0J#8:+VY9FEfS~"},{"width":1200,"height":1800,"tw":1200,"th":1800,"alt":"... allerdings scheint keiner seiner Pläne zu klappen.","index":11,"blurhash":"L3By%45r000M4Tr;57E20$}@_3^j"},{"width":1200,"height":800,"tw":1200,"th":800,"alt":"&quot;Bringt eure Toten raus!&quot;","index":12,"blurhash":"LLDkSwE3Irof}rRl9w%1n,s,EM%1"},{"width":1200,"height":800,"tw":1200,"th":800,"alt":"Auch die Entführung von Jane (Luisa Stark) läuft komplett schief.","index":13,"blurhash":"LRDkiC}@xYf5JAbIR+Ip0#EMR+oL"},{"width":1200,"height":800,"tw":1200,"th":800,"alt":"Maggy (Carina Sattler) ist mit der Situation überfordert.","index":14,"blurhash":"L5Ac3@1i9F%h0drVEf-B0J-W}]9Z"},{"width":1200,"height":800,"tw":1200,"th":800,"alt":"Wenn alle Pläne schief laufen hilft nur Trost…","index":15,"blurhash":"LCD[5]01SP}q^*4:?GM{1K+[-:9a"},{"width":1200,"height":1800,"tw":1200,"th":1800,"alt":"... oder Alkohol.","index":16,"blurhash":"L8DH]d0;=xn400-BsDa#0#}lEOb_"},{"width":1200,"height":800,"tw":1200,"th":800,"alt":"Niemand überlebt ein Duell mit dem Doc.","index":17,"blurhash":"L7CE,#}W0fELI.=xIp5R1NEjwJWA"},{"width":1200,"height":1800,"tw":1200,"th":1800,"alt":"Ben (Leon Rörig) und Frank (Louis Noe) sind dem Schatz in der Mine auf der Spur.","index":18,"blurhash":"LfGQ#7~CxHIV%H%LS1RjRlNKofoe"},{"width":1200,"height":1800,"tw":1200,"th":1800,"alt":"Der Bürgermeister (Tobias Knechtel) mischt jetzt auch mit.","index":19,"blurhash":"L7Dt@aIr_1~BBp^jbvNw00=_D*9u"},{"width":1200,"height":800,"tw":1200,"th":800,"alt":"Janes (Luisa Stark) Heulsirene ist die beste Foltermethode.","index":20,"blurhash":"LSEdDG5RtRIp}]Ipt7M|StR+xFR*"},{"width":1200,"height":800,"tw":1200,"th":800,"alt":"Eddie (Till Michel), Thomas (Yunus Sari) und Richie (Franek Wozniak) gehen leider leer aus.","index":21,"blurhash":"LCAj$*sA1vW;s.jtNbSf1ubH|way"},{"width":1200,"height":1800,"tw":1200,"th":1800,"alt":"Fesselnde Zweisamkeit zwischen Doc und Kate","index":22,"blurhash":"L4Au~p:RU^vf~pM|rX#R00%f-;xu"},{"width":1200,"height":800,"tw":1200,"th":800,"alt":"KABOOM","index":23,"blurhash":"L7B_rH}@0e=_58%2^jNH0|EM||%1"},{"width":1200,"height":800,"tw":1200,"th":800,"alt":"Ein kleines Feuerwerk zum Finale","index":24,"blurhash":"L15XJ;Sq0RG11CaTRN-200n.?CwE"}],"hell":[{"width":1200,"height":800,"tw":1200,"th":800,"alt":"Der Teufel (Jonas) betritt die Bühne","index":0,"blurhash":"LD9%q_Rk00%2~pay4noe9Fof-;NG"},{"width":1200,"height":800,"tw":1200,"th":800,"alt":"Ein Engel (Nele) berichtet dem Teufel von der mangelhaften Bösartigkeit der Hölle","index":1,"blurhash":"L35X7J0}9G}[XmnPV@o}0|].o}EM"},{"width":1200,"height":800,"tw":1200,"th":800,"alt":"Der Teufel beratschlagt sich mit Willi","index":2,"blurhash":"L46?V_s.0}I;$jWpJ7jZ1HNu}Z$j"},{"width":1200,"height":800,"tw":1200,"th":800,"alt":"Prof. Dr. Dr. Glutheiß (Nora) beratschläggt den Teufel und seine Assistantentin (Fernanda).","index":3,"blurhash":"L47]3RE}1v}ESeJ7wyW;1Iw{|_63"},{"width":1200,"height":800,"tw":1200,"th":800,"alt":"Belzebub (Nikodem) versucht Zeit zu zuschinden in dem er die Tochter des Teufels, Lucy (Elena), ablenkt.","index":4,"blurhash":"LB95.:5,Rj$*}rADV@$*t6a{aeof"},{"width":1200,"height":800,"tw":1200,"th":800,"alt":"Ein undercover Engel (Vanessa) tauscht sich mit Teufelchen (Lina und Nela) aus.","index":5,"blurhash":"L47]FrAW1I,?64sn,?S21Jw_}EN]"},{"width":1200,"height":800,"tw":1200,"th":800,"alt":"Lilith (Theresa) und Mammodia (Hatice) foltern den Engel (Vanessa) mit schiefem Flötenspiel.","index":6,"blurhash":"L69FvcTx5jrD?^-;rqM_8H?G+^EM"},{"width":1200,"height":800,"tw":1200,"th":800,"alt":"Lucy und der Engel lassen sich von Lilith und Mammodia verwöhnen, nachdem sie die Hölle gerettet haben.","index":7,"blurhash":"L89$eD}PE-0w0cAJxA-q5iSjwu-V"},{"width":1200,"height":800,"tw":1200,"th":800,"alt":"Alle Schauspieler bei der Verbeugung","index":8,"blurhash":"L57APWNH0Lxu-pR*IVxa0foL}@V["}],"kloster":[{"width":1200,"height":885,"tw":1200,"th":885,"alt":"Barde Mattes (Till Michel) kommt im Kloster Ramosa an.","index":0,"blurhash":"LDE:3z00L#8_0j~AD*t78^-;%Ns."},{"width":1200,"height":1285,"tw":1200,"th":1285,"alt":"Der Abt (Sebastian Sattler) ist ganz aus dem Häusschen. Hoher Besuch steht an.","index":1,"blurhash":"LBDcE:1457zT.Aoh9FvxZykrwaXU"},{"width":1200,"height":541,"tw":1200,"th":541,"alt":"Der Kaiser (Leonhard Rikart) kommt mit seinem Tross im Kloster Ramosa an.","index":2,"blurhash":"L6CP|-b;9uM{O?H=.Tk@00Ng#j,,"},{"width":1200,"height":1148,"tw":1200,"th":1148,"alt":"Hauptmann Lorenz (Anton Rikart) und Prinzessin Elisabeth( Marleen Pohl) schmieden finstere Pläne.","index":3,"blurhash":"LOJ@zhG^tm%19EzU-PxY03O@IYJC"},{"width":1200,"height":969,"tw":1200,"th":969,"alt":"Der Kaiser (Leonhard Rikart) im Gespräch mit Prinzessin Helen (Carina Sattler).","index":4,"blurhash":"LDC~#c7Q5vx_Ay={ogElDhM^V?$J"},{"width":1200,"height":1203,"tw":1200,"th":1203,"alt":"Prinzessin Helen (Carina Sattler) stellt dem Kaiser (Leonhard Rikart) ihre Dienstmagd Agnes (Toni Kummermehr) vor.","index":5,"blurhash":"L884GJ.A189i%OxvWaER9FITs%-j"},{"width":1200,"height":891,"tw":1200,"th":891,"alt":"Die Stumpfwaldhexe (Anna Rieder) steckt mit Prinzessin Elisabeth (Marleen Pohl) unter einer Decke.","index":6,"blurhash":"LFHLSY00D400S$S$^jrq00~9b{-;"},{"width":1200,"height":763,"tw":1200,"th":763,"alt":"Agnes (Toni Kummermehr) und Mattes (Till Michel) beobachten die Verschwörer.","index":7,"blurhash":"LRC?1BXUET-p~TWUI=%0o#WGRoR+"},{"width":1200,"height":1219,"tw":1200,"th":1219,"alt":"Das Fest zu Ehren des Kaisers ist in vollem Gange.","index":8,"blurhash":"LICG}h^SrA~q%~xIRjShITo~R.D$"},{"width":1200,"height":824,"tw":1200,"th":824,"alt":"Einen Toast auf alle Freunde","index":9,"blurhash":"L6DIzcE30hV?O]nh-44=009aof~9"},{"width":1200,"height":703,"tw":1200,"th":703,"alt":"Mystischer Rabentanz","index":10,"blurhash":"L15;?w#f5Ukv^+S+tIM{00TMw0wC"},{"width":1200,"height":843,"tw":1200,"th":843,"alt":"Agnes (Toni Kummermehr)","index":11,"blurhash":"LQFr62~B9vR:K*XTnOWB$exWIpIV"},{"width":1200,"height":676,"tw":1200,"th":676,"alt":"Die Verfolgten haben es sich im Lager von Anne (Anna Kummermehr) gemütlich gemacht.","index":12,"blurhash":"L88|kc~V%Lj]M|M{M{oe004:IVay"},{"width":1200,"height":835,"tw":1200,"th":835,"alt":"Die Magie des abendlichen Waldes","index":13,"blurhash":"L67Te3E156~E0n-T-PE8-ME8Ivs~"},{"width":1200,"height":1100,"tw":1200,"th":1100,"alt":"Das Schlaflied","index":14,"blurhash":"L45;k3$w0JIyi~jrOZR$9pM|$q$_"},{"width":1200,"height":1168,"tw":1200,"th":1168,"alt":"Mattes (Till Michel) wird von Anne (Anna Kummermehr) für den großen Kampf trainiert.","index":15,"blurhash":"LTJtF$}?$e-P9c-;I@S5xVIVxZIo"},{"width":1200,"height":678,"tw":1200,"th":678,"alt":"Agnes (Toni Kummermehr) beobachtet die Stumpfwaldhexe (Anna Rieder) beim Tränkebrauen.","index":16,"blurhash":"LDExtlSz02~U02E3-oRltj-UWBRk"},{"width":1200,"height":608,"tw":1200,"th":608,"alt":"Prinzessin Elisabeth (Marleen Pohl) hat Anne (Anna Kummermehr) gefangen genommen und in den Kerker gesperrt.","index":17,"blurhash":"LCGQ|C1FB:^w03-p$eo$}m#qIYM~"},{"width":1200,"height":1048,"tw":1200,"th":1048,"alt":"Hauptmann Lorenz (Anton Rikart) im entscheidenden Kampf gegen den Barden Mattes (Till Michel)","index":18,"blurhash":"LEFFHQ009$~W0MtR?F9Z8^~p9aD*"},{"width":1200,"height":757,"tw":1200,"th":757,"alt":"Der Barde ist besiegt!","index":19,"blurhash":"L8Eo#y^h000J00Di~q?a~ptSVrD%"},{"width":1200,"height":481,"tw":1200,"th":481,"alt":"Die Stumpfwaldhexe (Anna Rieder) hat ein Auge auf Hauptmann Lorenz (Anton Rikart) geworfen.","index":20,"blurhash":"L7F5jP%g000303wGER-m004:^*~V"},{"width":1200,"height":674,"tw":1200,"th":674,"alt":"Graf Philipp (Leon Rörig) hört sich an, was Prinzessin Helen (Carina Sattler) und ihre Freunde zu sagen haben.","index":21,"blurhash":"L3BzRj4,008z00?H^,D*DOMdYO_L"}],"kristall":[{"width":1200,"height":735,"tw":1200,"th":735,"alt":"Eure Majestät, der Kristall funktioniert nicht mehr!","index":0,"blurhash":"L3C~h,Pm0000000z$x#R2qDiR7_N"},{"width":1200,"height":800,"tw":1200,"th":800,"alt":"Der Kaiser befiehlt seinem Hauptmann die verschwundene Prinzessin zu finden.","index":1,"blurhash":"L5Bptf4:00,]L#It4;?G3C%0~Aou"},{"width":1200,"height":755,"tw":1200,"th":755,"alt":"Hauptmann Arno (Louis Noe)","index":2,"blurhash":"LMG8T800~AJWIVxsNHe.0M?ZIqs,"},{"width":1200,"height":723,"tw":1200,"th":723,"alt":"Kaiserin Theresa (Carina Sattler)","index":3,"blurhash":"L37w?H=m00%h00JA*0it0cV[^kOF"},{"width":1200,"height":839,"tw":1200,"th":839,"alt":"Shoppingtour für das Lieblingskind","index":4,"blurhash":"LdIgAg={Fc$%~T-TV?W;tRa_nPR-"},{"width":1200,"height":850,"tw":1200,"th":850,"alt":"Der &quot;Ich-schenke-meinem-Lieblingskind-alles-was-es-sich-wünscht-Tag!&quot;","index":5,"blurhash":"LAF4[#.T0o*0tnPC?I~WAItm_2%2"},{"width":1200,"height":1000,"tw":1200,"th":1000,"alt":"&quot;Bring deiner blöden Tochter einmal Manieren bei!&quot;","index":6,"blurhash":"LHD+-[07%MtL9l%%t8MwET%hbcVr"},{"width":1200,"height":801,"tw":1200,"th":801,"alt":"Merle (Luisa Stark)","index":7,"blurhash":"LD7_B,RvD.xS4,oBs%bJZxoax@Rr"},{"width":1200,"height":823,"tw":1200,"th":823,"alt":"Wellnessprogramm für Emily (Anna Kummermehr)","index":8,"blurhash":"LBB:2J5x05~C4@ku-?V}0g-V?HE4"},{"width":1200,"height":801,"tw":1200,"th":801,"alt":"Kaiser Richard (Anton Rikart)","index":9,"blurhash":"L9DI%d~kj9Gw0LE59w#i00Q;EAIA"},{"width":1200,"height":897,"tw":1200,"th":897,"alt":"Der Leibarzt (Julian Peters) übergibt seinem Freund Theodor (Marc Becker) das Waisenkind","index":10,"blurhash":"LAC$i*$|15?wJpJBxu-;9s-;-pD%"},{"width":1200,"height":795,"tw":1200,"th":795,"alt":"Irgendwie gehen alle Uhren falsch…","index":11,"blurhash":"L9B{$A5603^I?cMwIvt30nrV~VS~"},{"width":1200,"height":888,"tw":1200,"th":888,"alt":"&quot;Beruhige dich mein Engelchen!&quot;","index":12,"blurhash":"L8CY%SWH00%h0MIq?a-V01xu~pD%"},{"width":1200,"height":810,"tw":1200,"th":810,"alt":"Der Kaiser verlässt schwer bewacht seinen Palast.","index":13,"blurhash":"LTEVH7~Vxu%1~V-:bHRjjFt6M|IV"},{"width":1200,"height":779,"tw":1200,"th":779,"alt":"Ein Hoffnungsschimmer für die traumlose Welt.","index":14,"blurhash":"LE7n7I-aD|IltEoFafWOE1R:xwoO"},{"width":1200,"height":759,"tw":1200,"th":759,"alt":"Merle träumt von ihrer Vergangenheit.","index":15,"blurhash":"L4DQ]NA70vm[0cI.t0i^}4=g$:kB"},{"width":1200,"height":1128,"tw":1200,"th":1128,"alt":"&quot;Ich bin die Ballkönigin? Ahhhh!&quot;","index":16,"blurhash":"LIF4WM}@0g4.AaJBWBaeMwRP%2-;"},{"width":1200,"height":767,"tw":1200,"th":767,"alt":"Der Professor (Jack Stricker)","index":17,"blurhash":"LIEB:S560ds8~9NaIqi^W*oNoOjI"},{"width":1200,"height":796,"tw":1200,"th":796,"alt":"Jens (Leon Rörig) testet die Traummaschine&quot;freiwillig&quot;.","index":18,"blurhash":"LODIakt70gi_~AofE2aKEMa#xZj["},{"width":1200,"height":813,"tw":1200,"th":813,"alt":"Archibald (Till Michel) freut sich, dass die Traummaschine funktioniert.","index":19,"blurhash":"LVFEP.xt0#nP}?t6E3aLJAj[xFWX"},{"width":1200,"height":736,"tw":1200,"th":736,"alt":"Emily wird auf die Probe gestellt.","index":20,"blurhash":"L5FN#a~X02NZ00Ip]-s,00IT=eb0"},{"width":1200,"height":857,"tw":1200,"th":857,"alt":"Arno stellt sich gegen die Garde.","index":21,"blurhash":"L4CO|J^k005800JN-l$f2h9w}c%1"}],"maleficarum":[{"width":1200,"height":800,"tw":1200,"th":800,"alt":"Georg (Leon Rörig) trifft das erste Mal auf Klara (Luisa Stark)","index":0,"blurhash":"L5DIj_0000~A02~A~A4:0L-noN-p"},{"width":1200,"height":800,"tw":1200,"th":800,"alt":"Barde Mattes wird für seine Frechheit abgeführt","index":1,"blurhash":"L9F;~Fvx}+#P01J:XUtS01tm02Ne"},{"width":1200,"height":800,"tw":1200,"th":800,"alt":"Pater Heinrich (Louis Noe) spricht zu der Gemeinde","index":2,"blurhash":"L8Ch~A0h0Lk6oanhxbR:00=|~AV@"},{"width":1200,"height":800,"tw":1200,"th":800,"alt":"Die &quot;Garde&quot; ...","index":3,"blurhash":"L6EUr;0y0ezpujBipH~C0O0w~BwN"},{"width":1200,"height":800,"tw":1200,"th":800,"alt":" ...wird von Maren ordentlich auf Vordermann gebracht.","index":4,"blurhash":"L7ByXCRj}qv}00Eh9vNZ00?GS%kr"},{"width":1200,"height":800,"tw":1200,"th":800,"alt":"Klara (Luisa Stark)","index":5,"blurhash":"L7A+{Va101?a01S#~AnOIo%2t7E2"},{"width":1200,"height":800,"tw":1200,"th":800,"alt":"Helene (Carina Sattler) und ihr Mann Wilhelm (Marc Becker)","index":6,"blurhash":"L5E2IR00I[Kc00_Lr_Z*00}@^*J,"},{"width":1200,"height":800,"tw":1200,"th":800,"alt":"Barde Mattes (Till Michel)","index":7,"blurhash":"L7Ch=[010g~W01-p=|Ioni-;VtMx"},{"width":1200,"height":800,"tw":1200,"th":800,"alt":"Die Gräfin wünscht eure Gegenwart","index":8,"blurhash":"LCAl^G$y9t~U9uX9%2Ip01NI%29a"},{"width":1200,"height":800,"tw":1200,"th":800,"alt":"Wilhelm (Marc Becker) macht Pater Markus (Jack Stricker) schwere Vorwürfe","index":9,"blurhash":"LAA]+[014o~V01?bxZD*0LkC^+E1"},{"width":1200,"height":800,"tw":1200,"th":800,"alt":"Maren wird von den Hexenjägern gefangen genommen","index":10,"blurhash":"L6C#VmL00~{fAaWCs.sm00Zi=xB."},{"width":1200,"height":800,"tw":1200,"th":800,"alt":"&quot;Aber eure Durchlauchtigkeit, es gibt doch auch Nachtisch&quot;","index":11,"blurhash":"L4AS--kq00$20LIp~B-o0M$fo}Ek"},{"width":1200,"height":800,"tw":1200,"th":800,"alt":"Heinrich Kramer (Louis Noe)","index":12,"blurhash":"LUD[tn~VEzI;57Ioxat6I:WBw_sn"},{"width":1200,"height":1800,"tw":1200,"th":1800,"alt":"Maren auf dem Scheiterhaufen","index":13,"blurhash":"LB8:#9M|02^*S#jsjFj[02t7~VD*"},{"width":1200,"height":800,"tw":1200,"th":800,"alt":"Fürstbischof Reinhard (Anton Rikart) eilt zur Hilfe","index":14,"blurhash":"L784MR00%1t7W=n$WBfl00~pRjRj"},{"width":1200,"height":800,"tw":1200,"th":800,"alt":"Mattes (Till Michel) und Helene (Carina Sattler)","index":15,"blurhash":"LED]0h^j0yMx?wM{Ion#AIE1-or="},{"width":1200,"height":800,"tw":1200,"th":800,"alt":"&quot;Ich will, dass du ein Gedicht über meine Schönheit verfasst&quot;","index":16,"blurhash":"L2C~n|@;041T00xaQl9X01K,=Z~7"},{"width":1200,"height":1800,"tw":1200,"th":1800,"alt":"Die Inquisitoren kommen in Ramsen an","index":17,"blurhash":"L5B2}uPU0e*xDiNbNdxZ0Lvz}@L2"},{"width":1200,"height":800,"tw":1200,"th":800,"alt":"Maren wird im Gefängnis versorgt","index":18,"blurhash":"L29Zv5~U009vAw4;RP~V00tR~VVs"},{"width":1200,"height":800,"tw":1200,"th":800,"alt":"Die finale Konfrontation","index":19,"blurhash":"L7AI#@kC00vg1Hr@-UOq00WC~po}"},{"width":1200,"height":800,"tw":1200,"th":800,"alt":"Klara (Luisa Stark) und Georg (Leon Rörig) verstecken sich im Wald","index":20,"blurhash":"LCF;Iz~FNBRYMsImWBt99DE1NzoY"}],"nexus":[{"width":1200,"height":800,"tw":1200,"th":800,"alt":"Die erste Lesung des Stücks","index":0,"blurhash":"L797Fa9xbw-;};EQWVRingp0%gR-"},{"width":1200,"height":800,"tw":1200,"th":800,"alt":"Captain Kuschel belauscht die Proben","index":1,"blurhash":"LNF$;go#K7-;.TRj-;V??wM{ROs:"},{"width":1200,"height":800,"tw":1200,"th":800,"alt":"Hunter (Anton Rikart) lässt sich vom Barkeeper (Tobias Knechtel) einen Drink mixen.","index":2,"blurhash":"LBBV9q0z55}t0d^RxaE09[Rh$+T2"},{"width":1200,"height":900,"tw":1200,"th":900,"alt":"Collin Charleston (Leon Rörig) und Delaya Delloraine (Vanessa Carduck) berichten stets live vor Ort.","index":3,"blurhash":"L5A9ss_40vRO]#Mw9]~E0v9ZnTr:"},{"width":1200,"height":675,"tw":1200,"th":675,"alt":"Blade (Louis Noe) bekommt von Nyra (Theresa Kummermehr) und Alesa (Carina Sattler)  Informationen zum Neurochip.","index":4,"blurhash":"LPA^3NoMj9R[IQxxxzoZIot9WAt5"},{"width":1200,"height":800,"tw":1200,"th":800,"alt":"Assistenzarzt (Fynn Hüttmann) untersucht einen Patienten (Theo Kummermehr) nach dem Experiment.","index":5,"blurhash":"LIFq?;~A~U-pw|xt$%s:4mE29vRj"},{"width":1200,"height":1800,"tw":1200,"th":1800,"alt":"KABOOM","index":6,"blurhash":"LEL:W1sr00Z~0}t20%S%00aKu6%L"},{"width":1200,"height":800,"tw":1200,"th":800,"alt":"Ein wilder Tanz einstudiert von Carina Sattler","index":7,"blurhash":"L5G@lN:N001P5Z5SRi0h00~C--Rj"},{"width":1200,"height":960,"tw":1200,"th":960,"alt":"Xion (Yunus Sari) und Ripper (Jonas Berst) versuchen Aria (Elena Mattheis) Implantate zu entnehmen.","index":8,"blurhash":"L9ELyJ?X004r~nxs0ME34qi|krSO"},{"width":1200,"height":675,"tw":1200,"th":675,"alt":"Die Bar “High Volate” ist ein beliebter Treffpunkt für die Crew.","index":9,"blurhash":"L55;wYsI53s|NWNEnNn$I%V;-ttV"},{"width":1200,"height":800,"tw":1200,"th":800,"alt":"Dante (Sebastian Sattler) verliert gegen die Kinder (Nikodem, Lina, Nela) beim Uno.","index":10,"blurhash":"L9ELHXL#;d5U_3}@Hqx^tlbYWBR,"},{"width":1200,"height":800,"tw":1200,"th":800,"alt":"Blade (Louis Noe) erklärt seinen bösen Masterplan.","index":11,"blurhash":"L8I:wK^*000M^Pxaxu9b00D+_1~A"},{"width":1200,"height":675,"tw":1200,"th":675,"alt":"Der Abschlusstanz einstudiert von Maria Misling","index":12,"blurhash":"LF8:t.RkE3%0~ARkIp%0X8R+V[t6"},{"width":1200,"height":800,"tw":1200,"th":800,"alt":"Raven (Lea Bohn) hackt sich in das System während Vega (Nele Rörig) sie deckt.","index":13,"blurhash":"L4C77t008#$O00~q$TbKI58_K4R:"},{"width":1200,"height":800,"tw":1200,"th":800,"alt":"Die Chrome Schwestern (Magdalena Misling, Maria Misling, Nora Bidinger) geben sich siegessicher.","index":14,"blurhash":"LKD@Rq2rEH{xxs$2R;J:5h,@kEJU"},{"width":1200,"height":1200,"tw":1200,"th":1200,"alt":"Es geht Nyra (Theresa Kummermehr) an den Kragen.","index":15,"blurhash":"LLH^O,0g9u9Z~BofE2sT57%1aetR"}],"proben":[{"width":1200,"height":795,"tw":1200,"th":795,"alt":"Was darf in keinem romantischen Stück fehlen?- Eine heimliche Fensterszene.","index":0,"blurhash":"L8A,zkt700-;~qxuD%ayIUxu-;%M"},{"width":1200,"height":795,"tw":1200,"th":795,"alt":"Till hinter Gittern","index":1,"blurhash":"L4BzC4~q%M%M_3t79Ft700M{D%M{"},{"width":1200,"height":795,"tw":1200,"th":795,"alt":"Noah kümmert sich um die Lichttechnik.","index":2,"blurhash":"LADJO}~qxuWBt7%Mt7IURjt7WBWB"},{"width":1200,"height":795,"tw":1200,"th":795,"alt":"Spaß beim Soundcheck","index":3,"blurhash":"L6C6+9Rj%M9F~qt74n-;-;D%%Mof"},{"width":1200,"height":795,"tw":1200,"th":795,"alt":"Voller Einsatz beim Umbau","index":4,"blurhash":"L8Ad7fWBD%9F9FIU9F%M9FRj~q-;"},{"width":1200,"height":795,"tw":1200,"th":795,"alt":"Bei der Probe fehlen auf dem Tisch noch die leckeren Speisen.","index":5,"blurhash":"LKECwdRj~qM{9FWBt7WBxuxuM{t7"},{"width":1200,"height":1812,"tw":1200,"th":1812,"alt":"Emma (Toni) hat Hans (Till) auf frischer Tat ertappt.","index":6,"blurhash":"LDEfTi_3IUWB~qWBayof009Fxuof"},{"width":1200,"height":1812,"tw":1200,"th":1812,"alt":"Moon aka Anna, wird von ihren Freunden getröstet.","index":7,"blurhash":"L4DJO}9F000000-;9FM{00%M~q-;"},{"width":1200,"height":795,"tw":1200,"th":795,"alt":"Die Musik ist gut!","index":8,"blurhash":"L9Ci~;9F9F~q4n_3of9FM{fQt7M{"},{"width":1200,"height":795,"tw":1200,"th":795,"alt":"Anton wird verkabelt.","index":9,"blurhash":"L8B:vz4n_300~qD%-;9F4n?bD%?b"},{"width":1200,"height":795,"tw":1200,"th":795,"alt":"Kampftraining für das Finale","index":10,"blurhash":"L7FFss~q4n%M00IUIUxu00IUt7j["},{"width":1200,"height":795,"tw":1200,"th":795,"alt":"Die Schönste Frau von allen gar…","index":11,"blurhash":"L2Ad7f~q00~qt7t7t7j[of%MD%9F"},{"width":1200,"height":1600,"tw":1200,"th":1600,"alt":"Ritter Tobi bereit für die nächste Schlacht!","index":12,"blurhash":"LAD0Go_39Fof~q?bIUD%-;xuM{M{"},{"width":1200,"height":1600,"tw":1200,"th":1600,"alt":"Der Schlussstein wird eingesetzt… gemalt.","index":13,"blurhash":"LFDvfy_3~qxu_34n?bt7~qIU?b%M"},{"width":1200,"height":795,"tw":1200,"th":795,"alt":"Im Kerker","index":14,"blurhash":"L6C?r]Rj009F~qD%M{ofM{%MWBxu"},{"width":1200,"height":795,"tw":1200,"th":795,"alt":"Daumen hoch für die Premiere.","index":15,"blurhash":"L8CGS+009F~q-;D%-;j[?bIUay-;"},{"width":1200,"height":795,"tw":1200,"th":795,"alt":"Gut verkabelt","index":16,"blurhash":"L9AJ~Aof004n00D%~qxuRjofofof"},{"width":1200,"height":795,"tw":1200,"th":795,"alt":"Die requisiten werden angemalt","index":17,"blurhash":"L4B:vz~q0000xu4nt7_3D%Rjayt7"},{"width":1200,"height":795,"tw":1200,"th":795,"alt":"Pater Markus (Jack) lehrt Klara (Luisa) das Lesen.","index":18,"blurhash":"LBFFss9F-;~qt79Fof%M-;%MM{j["},{"width":1200,"height":795,"tw":1200,"th":795,"alt":"Das Textlernen erfordert volle Konzentration","index":19,"blurhash":"L3BM_P0000D%009Fof_39F~qIUIU"},{"width":1200,"height":795,"tw":1200,"th":795,"alt":"Rüstung bei 30 Grad erfordert eine Abkühlung","index":20,"blurhash":"L58XFB00D%~q%MIU?bIURjWB-;D%"},{"width":1200,"height":795,"tw":1200,"th":795,"alt":"Klara (Luisa) ist misstrauisch.","index":21,"blurhash":"LHECwd~q?b%MRjD%IURjIUD%IURj"},{"width":1200,"height":795,"tw":1200,"th":795,"alt":"We are familiy!.","index":22,"blurhash":"L37d%r?b000000D%_3?b4nof?bof"},{"width":1200,"height":795,"tw":1200,"th":795,"alt":"Kolpinghtheater Ramsen am Apparat. Wie viele Karten darf ich reservieren?","index":23,"blurhash":"LJCi~;~qt7M{004nM{xuxuxuayWB"},{"width":1200,"height":795,"tw":1200,"th":795,"alt":"Der Regisseur nimmt ein unfreiwilliges Bad","index":24,"blurhash":"LED0GoRj~q%M00%M4nIU?bD%-;of"},{"width":1200,"height":795,"tw":1200,"th":795,"alt":"Alle sind unserer Gräfin (Anton) verfallen.","index":25,"blurhash":"L08Nqb0000~qxu00xu~q00~q%M00"},{"width":1200,"height":795,"tw":1200,"th":795,"alt":"Kulissenbau-Tutorial","index":26,"blurhash":"L7BWe~Rj_300t7Rjt7%M00~q00-;"},{"width":1200,"height":795,"tw":1200,"th":795,"alt":"Wallendes Haar, so wunderbar!","index":27,"blurhash":"L5B:vz~q9FD%0000fQIU?bxuxut7"},{"width":1200,"height":1811,"tw":1200,"th":1811,"alt":"Die Kulisse nimmt langsam Gestalt an","index":28,"blurhash":"L7CZbEM{00~qj[ayM{M{D%-;xu00"},{"width":1200,"height":795,"tw":1200,"th":795,"alt":"Heute malen wir die Kulisse in ein fröhliches Schwarz","index":29,"blurhash":"LHEo[I_3~q_3%M%M?b-;-;WBRjof"},{"width":1200,"height":795,"tw":1200,"th":795,"alt":"Stärkung nach der ganzen Arbeit","index":30,"blurhash":"LFDl{3~qIU?bxuM{M{t74nWBxuj["},{"width":1200,"height":795,"tw":1200,"th":795,"alt":"Regieanweisungen für einen Kampf","index":31,"blurhash":"L8EMLD~qD%M{00t7xuIU_3D%xuxu"},{"width":1200,"height":1811,"tw":1200,"th":1811,"alt":"Wenn die Requisiten noch nicht fertig sind, muss man improvisieren.","index":32,"blurhash":"LEECwdRjfQ9FM{M{WB9F~qt7t7IU"},{"width":1200,"height":795,"tw":1200,"th":795,"alt":"Hier kommt keiner vorbei!","index":33,"blurhash":"LEDvfyD%4n4n~qxu9FM{xut7IURj"},{"width":1200,"height":1811,"tw":1200,"th":1811,"alt":"Ihre böse Stiefschwester (Anna) ärgert Merle (Luisa)","index":34,"blurhash":"L5Gu,mD%~q0000_3WB-;004n00~q"},{"width":1200,"height":795,"tw":1200,"th":795,"alt":"Uh, das ist spitz!","index":35,"blurhash":"L38z.G00~qIU?bD%%MRj00-;WBj["},{"width":1200,"height":795,"tw":1200,"th":795,"alt":"Arno (Louis) erstattet der Kaiserin (Carina) Bericht","index":36,"blurhash":"LBD0Go~q4n9F00xu-;IU~qt7Rj%M"},{"width":1200,"height":795,"tw":1200,"th":795,"alt":"Die Bühne wird eingeleuchtet","index":37,"blurhash":"LIDcXT00~qD%t7%MM{%Mt7t7j[-;"},{"width":1200,"height":795,"tw":1200,"th":795,"alt":"Bei 30 Grad im Schatten darf auch der historisch nicht korrekte Sonnenschutz getragen werden.","index":38,"blurhash":"LCC%8J~qD%M{M{M{t7xu%MayWBxu"},{"width":1200,"height":1811,"tw":1200,"th":1811,"alt":"Auf, auf und davon!","index":39,"blurhash":"LBBg3u~qRjt7D%%M%M%MD%j[_3-;"},{"width":1200,"height":795,"tw":1200,"th":795,"alt":"Photobomb!","index":40,"blurhash":"L9Csjj9F00_3~qWB00t7~qxuIU-;"},{"width":1200,"height":795,"tw":1200,"th":795,"alt":"Immer schön Lächeln","index":41,"blurhash":"LGF68|Rj00%M00xu~qM{%MRjM{D%"}],"sagenhaft":[{"width":1200,"height":800,"tw":1200,"th":800,"alt":"“Die Sage beginnt mit der Kindheit der Schwestern (in der Kindheit verkörpert von Lina Roos & Nela Rödel)”","index":0,"blurhash":"L683b*GXE0IA-aJ}$jwc0c#7xwx^"},{"width":1200,"height":800,"tw":1200,"th":800,"alt":"“Die beiden älteren Schwestern (Elena Matheis & Nele Rörig)...”","index":1,"blurhash":"L5718Vm$0cS*5Mf$%5oi4,T2-tng"},{"width":1200,"height":800,"tw":1200,"th":800,"alt":"“... machen ihrer jüngeren Schwester (Theresa Kummermehr) das Leben zur Hölle.”","index":2,"blurhash":"LEASTgwF0cOx9?Sh-WwuEGkDxxR#"},{"width":1200,"height":1799,"tw":1200,"th":1799,"alt":"“Der Ritter Berthold von Winzingen (Jonas Berst) ist mit seinem Knappen (Nikodem Wozniak) auf der Jagd.”","index":3,"blurhash":"L49?@3mP~Uo,0G}h9aY80z00o}E+"},{"width":1200,"height":1799,"tw":1200,"th":1799,"alt":"“Im Wald trifft der Ritter (Jonas Berst) auf die junge Schwester Emma (Theresa Kummermehr) und verliebt sich.”","index":4,"blurhash":"L75690DVMg.gHyyRo_MhZjkAtPMh"},{"width":1200,"height":1799,"tw":1200,"th":1799,"alt":"“Ein Heiratsanwärter (Raphael Klein) wird erst um den Finger gewickelt…”","index":5,"blurhash":"L42Yi2nIS8S+XYW5j^j_NAb#sjss"},{"width":1200,"height":1799,"tw":1200,"th":1799,"alt":"“... und dann mit einem Bären (Tobias Knechtel) vom Hof gejagt, nachdem er den Schwestern sein Vermögen überschrieben hatte.”","index":6,"blurhash":"LDBet8A00g}qI{s=$yEM0i$%^NEg"},{"width":1200,"height":1799,"tw":1200,"th":1799,"alt":"“Der Ritter und Emma brennen gemeinsam durch…”","index":7,"blurhash":"LB7K74M@NM-qxgjTt8alNOR$bXWI"},{"width":1200,"height":1799,"tw":1200,"th":1799,"alt":"“... und heiraten auf seiner Burg.”","index":8,"blurhash":"L45#PE?K59EeIcImWY$%0sNe-knn"},{"width":1200,"height":1656,"tw":1200,"th":1656,"alt":"“Ein Bote (Johannes Stüber) überbringt die Botschaft von der Heirat und fordert eine Mitgift.”","index":9,"blurhash":"L33[PtXroisD%Q%5oiR*xw$*bKNZ"},{"width":1200,"height":1799,"tw":1200,"th":1799,"alt":"“Die älteren Schwestern (Nele Rörig & Elena Matheis) schmieden einen Plan.”","index":10,"blurhash":"LH5}Uwx|S2RMIkV;s:o%RhRhW9k9"},{"width":1200,"height":1799,"tw":1200,"th":1799,"alt":"“Die Magd (Fernanda Fischer) soll das Gold vergraben…”","index":11,"blurhash":"L35E]JQWrr_MD*tltlMx4nyTM|IA"},{"width":1200,"height":1799,"tw":1200,"th":1799,"alt":"“... und dass sie niemandem davon erzählen kann, locken die Schwestern sie in den nahen Sumpf.”","index":12,"blurhash":"L01Ms8VgwErVyMMeyXohJ5TuO=Tc"},{"width":1200,"height":800,"tw":1200,"th":800,"alt":"“Der Ritter und Emma warten auf der Burg auf eine Antwort der Schwestern.”","index":13,"blurhash":"L55Npc#s9:KlJ1NWn#$o9pX9%7aI"},{"width":1200,"height":800,"tw":1200,"th":800,"alt":"“Ein Waldgeist (Vanessa Carduck) lässt die bösen Schwestern für ihre Taten büßen und zieht sie in den Sumpf.”","index":14,"blurhash":"L10Ka-Y+g7k=lRbXe.kpY+l.eQa0"},{"width":1200,"height":1799,"tw":1200,"th":1799,"alt":"“Emma erfährt vom Waldgeist von den Machenschaften ihrer Schwestern.”","index":15,"blurhash":"L64BI]=i$lS6f?bJoOn~A9EcNWn#"},{"width":1200,"height":800,"tw":1200,"th":800,"alt":"“Schließlich findet Ritter Berthold den Schatz und gründet das Kloster Ramosa.”","index":16,"blurhash":"LB6*Rlt:NiwcWaV=RiWU9WVqsRX7"},{"width":1200,"height":1799,"tw":1200,"th":1799,"alt":"“Die Chronistin (Nora Bidinger) führte durch die Geschichte.”","index":17,"blurhash":"L01V}JMv5J,9?]R3EA$JMdZ~ohfh"},{"width":1200,"height":800,"tw":1200,"th":800,"alt":"“Glückliche Gesichter nach der Premiere”","index":18,"blurhash":"L47mT{^k0xWGETI:WASi0vsl}]s+"}]}